gradcam/__init__.py
gradcam/gradcam.py
gradcam/utils.py
pytorch_gradcam-0.2.0.dist-info/METADATA
pytorch_gradcam-0.2.0.dist-info/WHEEL
pytorch_gradcam-0.2.0.dist-info/top_level.txt
pytorch_gradcam-0.2.0.dist-info/RECORD
