Metadata-Version: 2.1
Name: pytorch-gradcam
Version: 0.2.0
Summary: A Simple pytorch implementation of GradCAM, and GradCAM++
Home-page: https://github.com/vickyliin/gradcam_plus_plus-pytorch
Author: vickyliin
Author-email: vickyliinn@gmail.com
License: UNKNOWN
Keywords: GradCam CNN visualization heatmap
Platform: UNKNOWN
Classifier: Development Status :: 3 - Alpha
Classifier: Intended Audience :: Developers
Classifier: Topic :: Scientific/Engineering :: Artificial Intelligence
Classifier: Topic :: Scientific/Engineering :: Visualization
Classifier: License :: OSI Approved :: MIT License
Classifier: Programming Language :: Python :: 3
Requires-Python: >=3.5, <4
Requires-Dist: opencv-python
Requires-Dist: numpy
